copernicusmarine/__init__.py
copernicusmarine/catalogue_parser/__init__.py
copernicusmarine/catalogue_parser/catalogue_parser.py
copernicusmarine/catalogue_parser/models.py
copernicusmarine/command_line_interface/__init__.py
copernicusmarine/command_line_interface/copernicus_marine.py
copernicusmarine/command_line_interface/exception_handler.py
copernicusmarine/command_line_interface/group_describe.py
copernicusmarine/command_line_interface/group_get.py
copernicusmarine/command_line_interface/group_login.py
copernicusmarine/command_line_interface/group_subset.py
copernicusmarine/command_line_interface/utils.py
copernicusmarine/core_functions/click_custom_class.py
copernicusmarine/core_functions/credentials_utils.py
copernicusmarine/core_functions/custom_open_zarr.py
copernicusmarine/core_functions/custom_s3_store_zarr_v2.py
copernicusmarine/core_functions/custom_s3_store_zarr_v3.py
copernicusmarine/core_functions/deprecated_options.py
copernicusmarine/core_functions/describe.py
copernicusmarine/core_functions/documentation_utils.py
copernicusmarine/core_functions/environment_variables.py
copernicusmarine/core_functions/exceptions.py
copernicusmarine/core_functions/fields_query_builder.py
copernicusmarine/core_functions/get.py
copernicusmarine/core_functions/login.py
copernicusmarine/core_functions/marine_datastore_config.py
copernicusmarine/core_functions/models.py
copernicusmarine/core_functions/request_structure.py
copernicusmarine/core_functions/services_utils.py
copernicusmarine/core_functions/sessions.py
copernicusmarine/core_functions/subset.py
copernicusmarine/core_functions/utils.py
copernicusmarine/download_functions/chunk_calculator.py
copernicusmarine/download_functions/download_original_files.py
copernicusmarine/download_functions/download_sparse.py
copernicusmarine/download_functions/download_zarr.py
copernicusmarine/download_functions/subset_parameters.py
copernicusmarine/download_functions/subset_xarray.py
copernicusmarine/download_functions/utils.py
copernicusmarine-2.2.3.dist-info/LICENSE.txt
copernicusmarine-2.2.3.dist-info/METADATA
copernicusmarine-2.2.3.dist-info/WHEEL
copernicusmarine-2.2.3.dist-info/entry_points.txt
copernicusmarine-2.2.3.dist-info/RECORD
