Metadata-Version: 2.3
Name: copernicusmarine
Version: 2.2.3
Summary: Command line interface and Python API for accessing Copernicus Marine data and related services.
License: EUPL-1.2
Author: Copernicus Marine User Support
Author-email: servicedesk.cmems@mercator-ocean.eu
Requires-Python: >=3.9
Classifier: License :: OSI Approved :: European Union Public Licence 1.2 (EUPL 1.2)
Classifier: Programming Language :: Python :: 3
Classifier: Programming Language :: Python :: 3.9
Classifier: Programming Language :: Python :: 3.10
Classifier: Programming Language :: Python :: 3.11
Classifier: Programming Language :: Python :: 3.12
Classifier: Programming Language :: Python :: 3.13
Requires-Dist: arcosparse (>=0.4.2,<0.5.0)
Requires-Dist: boto3 (>=1.26)
Requires-Dist: click (>=8.0.4,!=8.2.0)
Requires-Dist: dask (>=2022)
Requires-Dist: h5netcdf (>=1.4.0,<2.0.0)
Requires-Dist: numpy (>=1.23.0)
Requires-Dist: pydantic (>=2.9.1,<3.0.0)
Requires-Dist: pystac (>=1.8.3)
Requires-Dist: requests (>=2.27.1)
Requires-Dist: semver (>=3.0.2)
Requires-Dist: setuptools (>=68.2.2)
Requires-Dist: tqdm (>=4.65.0)
Requires-Dist: xarray (>=2023.4.0)
Requires-Dist: zarr (>=2.13.3)
